jumpdiff/__init__.py
jumpdiff/binning.py
jumpdiff/formulae.py
jumpdiff/jd_process.py
jumpdiff/kernels.py
jumpdiff/moments.py
jumpdiff/parameters.py
jumpdiff/q_ratio.py
jumpdiff-0.4.2.dist-info/LICENSE
jumpdiff-0.4.2.dist-info/METADATA
jumpdiff-0.4.2.dist-info/WHEEL
jumpdiff-0.4.2.dist-info/top_level.txt
jumpdiff-0.4.2.dist-info/RECORD
