Metadata-Version: 2.1
Name: jumpdiff
Version: 0.4.2
Summary: JumpDiff: Non-parametric estimators for jump-diffusion processes for Python.
Home-page: https://github.com/LRydin/JumpDiff
Author: Leonardo Rydin Gorjão
Author-email: leonardo.rydin@gmail.com
License: MIT License
Platform: UNKNOWN
Classifier: Programming Language :: Python :: 3
Classifier: License :: OSI Approved :: MIT License
Classifier: Operating System :: OS Independent
Requires-Python: >=3.5
Requires-Dist: numpy
Requires-Dist: scipy
Requires-Dist: sympy
